WSIdemerger/Colour_standardisation.py
WSIdemerger/Patches_generation.py
WSIdemerger/__init__.py
WSIdemerger-0.1.8.dist-info/LICENSE
WSIdemerger-0.1.8.dist-info/METADATA
WSIdemerger-0.1.8.dist-info/WHEEL
WSIdemerger-0.1.8.dist-info/top_level.txt
WSIdemerger-0.1.8.dist-info/RECORD
