Metadata-Version: 2.1
Name: WSIdemerger
Version: 0.1.8
Summary: A package for extracting image patches from SVS files and performing color normalization
Home-page: https://github.com/yourusername/WSI_Preprocessing
Author: Thirteen
Author-email: 506607814@qq.com
License: MIT
Classifier: Programming Language :: Python :: 3
Classifier: License :: OSI Approved :: MIT License
Classifier: Operating System :: OS Independent
Requires-Python: >=3.6
License-File: LICENSE
Requires-Dist: pandas
Requires-Dist: openslide-python
Requires-Dist: Pillow
Requires-Dist: numpy
Requires-Dist: scikit-image
Requires-Dist: tqdm
Requires-Dist: opencv-python
Requires-Dist: staintools
